Laboratorio3/fsm_control.sv
module fsm_control(
  input  logic        clk,
  input  logic        rst_n,
  
  // Entradas de control
  input  logic        btn_sel_i,
  input  logic        time_up_i,
  input  logic        cards_match_i,       // desde datapath
  input  logic        pause_done_i,       // desde datapath
  input  logic        auto_pick1_valid_i, // desde datapath
  input  logic        auto_pick2_valid_i, // desde datapath
  input  logic        match_happened_i,   // indica que ocurrió un match
  
  // Salidas de control
  output logic        select_first_card_o,
  output logic        select_second_card_o,
  output logic        auto_select_first_o,
  output logic        auto_select_second_o,
  output logic        match_found_o,
  output logic        start_pause_o,
  output logic        end_turn_o,          // cambio de jugador por fallo
  output logic        extra_turn_o,        // turno extra por acierto
  output logic        restart_timer_o,
  
  // Estado actual (para debug/display)
  output logic [1:0]  current_state_o
);

  // Estados simples
  localparam [1:0] S_IDLE  = 2'b00;
  localparam [1:0] S_ONE   = 2'b01; 
  localparam [1:0] S_PAUSE = 2'b10;

  // Registro de estado
  logic [1:0] state, next_state;

  // ================ ESTADO ACTUAL ================
  always_ff @(posedge clk or negedge rst_n) begin
    if (!rst_n) 
      state <= S_IDLE;
    else        
      state <= next_state;
  end

  // ================ PRÓXIMO ESTADO ================
  always_comb begin
    // Defaults
    next_state = state;
    
    case(state)
      S_IDLE: begin
        if (time_up_i && auto_pick1_valid_i) begin
          next_state = S_ONE;  // auto-selección primera carta
        end else if (btn_sel_i) begin
          next_state = S_ONE;  // selección manual primera carta
        end
      end
      
      S_ONE: begin
        if (time_up_i && auto_pick2_valid_i) begin
          if (cards_match_i) 
            next_state = S_IDLE;  // acierto directo
          else 
            next_state = S_PAUSE; // fallo, mostrar cartas
        end else if (btn_sel_i) begin
          if (cards_match_i)
            next_state = S_IDLE;  // acierto directo  
          else
            next_state = S_PAUSE; // fallo, mostrar cartas
        end
        // Si hubo match por otra lógica, también ir a IDLE
        else if (match_happened_i) begin
          next_state = S_IDLE;
        end
      end
      
      S_PAUSE: begin
        if (pause_done_i) begin
          next_state = S_IDLE;
        end
      end
      
      default: next_state = S_IDLE;
    endcase
  end

  // ================ SALIDAS ================
  always_comb begin
    // Defaults
    select_first_card_o  = 1'b0;
    select_second_card_o = 1'b0;
    auto_select_first_o  = 1'b0;
    auto_select_second_o = 1'b0;
    match_found_o        = 1'b0;
    start_pause_o        = 1'b0;
    end_turn_o           = 1'b0;
    extra_turn_o         = 1'b0;
    restart_timer_o      = 1'b0;
    
    case(state)
      S_IDLE: begin
        if (time_up_i && auto_pick1_valid_i) begin
          auto_select_first_o = 1'b1;
          restart_timer_o     = 1'b1;
        end else if (btn_sel_i) begin
          select_first_card_o = 1'b1;
        end
      end
      
      S_ONE: begin
        if (time_up_i && auto_pick2_valid_i) begin
          auto_select_second_o = 1'b1;
          // La lógica de match se maneja en las transiciones de estado
        end else if (btn_sel_i) begin
          select_second_card_o = 1'b1;
          // La lógica de match se maneja en las transiciones de estado
        end
      end
      
      default: ;
    endcase

    // Salidas basadas en transiciones (no estados)
    if (state == S_ONE) begin
      if ((time_up_i && auto_pick2_valid_i) || btn_sel_i) begin
        if (cards_match_i) begin
          match_found_o   = 1'b1;
          extra_turn_o    = 1'b1;
          restart_timer_o = 1'b1;  // Reiniciar timer por acierto
        end else begin
          start_pause_o = 1'b1;
        end
      end
    end

    // También reiniciar timer si hubo match por la lógica inmediata del datapath
    if (match_happened_i) begin
      restart_timer_o = 1'b1;
    end

    if (state == S_PAUSE && pause_done_i) begin
      end_turn_o = 1'b1;  // cambio de jugador
    end
  end

  // Estado para debug
  assign current_state_o = state;

endmodule

Laboratorio3/tb_fsm_control.sv
// tb_fsm_control.sv — Testbench de transición de estados para fsm_control

`timescale 1ns/1ps

module tb_fsm_control;

  // -------------------- Reloj y reset --------------------
  logic clk;
  logic rst_n;

  localparam real CLK_PERIOD_NS = 10.0;

  initial begin
    clk = 1'b0;
    forever #(CLK_PERIOD_NS/2.0) clk = ~clk;
  end

  task automatic apply_reset;
    begin
      rst_n = 1'b0;
      repeat (3) @(posedge clk);
      rst_n = 1'b1;
      @(posedge clk);
    end
  endtask

  // -------------------- Señales hacia el DUT --------------------
  logic btn_sel_i;
  logic time_up_i;
  logic cards_match_i;
  logic pause_done_i;
  logic auto_pick1_valid_i;
  logic auto_pick2_valid_i;
  logic match_happened_i;

  // -------------------- Señales desde el DUT --------------------
  logic select_first_card_o;
  logic select_second_card_o;
  logic auto_select_first_o;
  logic auto_select_second_o;
  logic match_found_o;
  logic start_pause_o;
  logic end_turn_o;
  logic extra_turn_o;
  logic restart_timer_o;
  logic [1:0] current_state_o;

  // -------------------- Instancia del DUT --------------------
  fsm_control dut (
    .clk                   (clk),
    .rst_n                 (rst_n),
    .btn_sel_i             (btn_sel_i),
    .time_up_i             (time_up_i),
    .cards_match_i         (cards_match_i),
    .pause_done_i          (pause_done_i),
    .auto_pick1_valid_i    (auto_pick1_valid_i),
    .auto_pick2_valid_i    (auto_pick2_valid_i),
    .match_happened_i      (match_happened_i),
    .select_first_card_o   (select_first_card_o),
    .select_second_card_o  (select_second_card_o),
    .auto_select_first_o   (auto_select_first_o),
    .auto_select_second_o  (auto_select_second_o),
    .match_found_o         (match_found_o),
    .start_pause_o         (start_pause_o),
    .end_turn_o            (end_turn_o),
    .extra_turn_o          (extra_turn_o),
    .restart_timer_o       (restart_timer_o),
    .current_state_o       (current_state_o)
  );

  // -------------------- Helpers --------------------
  // Codificación conocida de estados en fsm_control
  localparam [1:0] S_IDLE  = 2'b00;
  localparam [1:0] S_ONE   = 2'b01;
  localparam [1:0] S_PAUSE = 2'b10;

  function automatic string state_to_str(input logic [1:0] s);
    case (s)
      S_IDLE:  state_to_str = "S_IDLE";
      S_ONE:   state_to_str = "S_ONE";
      S_PAUSE: state_to_str = "S_PAUSE";
      default: state_to_str = "UNKNOWN";
    endcase
  endfunction

  task automatic expect_state(input logic [1:0] expected, input string msg="");
    begin
      if (current_state_o !== expected) begin
        $error("[FALLÓ] Estado esperado=%s, observado=%s. %s",
               state_to_str(expected), state_to_str(current_state_o), msg);
      end else begin
        $display("[%0t ns] OK estado=%s. %s", $time, state_to_str(current_state_o), msg);
      end
    end
  endtask

  // Pulso de 1 ciclo para una señal
  task automatic pulse_one_cycle(ref logic signal_ref);
    begin
      signal_ref = 1'b1;
      @(posedge clk);
      signal_ref = 1'b0;
    end
  endtask

  // Limpia todas las entradas
  task automatic clear_inputs;
    begin
      btn_sel_i          = 1'b0;
      time_up_i          = 1'b0;
      cards_match_i      = 1'b0;
      pause_done_i       = 1'b0;
      auto_pick1_valid_i = 1'b0;
      auto_pick2_valid_i = 1'b0;
      match_happened_i   = 1'b0;
      @(posedge clk);
    end
  endtask

  // -------------------- Escenarios de prueba --------------------
  initial begin
    // Dump para waveform
    $dumpfile("tb_fsm_control.vcd");
    $dumpvars(0, tb_fsm_control);

    clear_inputs();
    apply_reset();

    // Tras reset debería estar en IDLE
    expect_state(S_IDLE, "Tras reset");

    // ------------------------------------------------------------
    // 1) Selección MANUAL: IDLE --btn_sel--> ONE
    // ------------------------------------------------------------
    $display("\n--- Caso 1: Seleccion manual de primera carta ---");
    btn_sel_i = 1'b1; // se evalúa en estado IDLE
    @(posedge clk);
    // En este ciclo, DUT debe poner select_first_card_o=1
    assert(select_first_card_o==1) else $error("Esperaba select_first_card_o=1 en IDLE con btn_sel_i");
    btn_sel_i = 1'b0;

    // En el siguiente ciclo, estado debe cambiar a S_ONE
    @(posedge clk);
    expect_state(S_ONE, "Despues de seleccionar primera carta (manual)");

    // ------------------------------------------------------------
    // 2) Segunda carta MANUAL con MATCH: ONE --btn_sel & cards_match--> IDLE
    // ------------------------------------------------------------
    $display("\n--- Caso 2: Segunda carta manual con MATCH ---");
    cards_match_i = 1'b1;
    btn_sel_i     = 1'b1; // trigger segunda selección
    @(posedge clk);
    // En este mismo ciclo deben levantarse flags de match
    assert(select_second_card_o==1) else $error("Esperaba select_second_card_o=1 al pulsar btn_sel en S_ONE");
    assert(match_found_o==1)        else $error("Esperaba match_found_o=1 con cards_match_i=1");
    assert(extra_turn_o==1)         else $error("Esperaba extra_turn_o=1 con cards_match_i=1");
    assert(restart_timer_o==1)      else $error("Esperaba restart_timer_o=1 con match");
    btn_sel_i     = 1'b0;
    cards_match_i = 1'b0;

    // Avanzar a que el estado retorne a IDLE
    @(posedge clk);
    expect_state(S_IDLE, "Regreso a IDLE tras match manual");

    // ------------------------------------------------------------
    // 3) Segunda carta MANUAL SIN MATCH: ONE --btn_sel & !match--> PAUSE
    // luego pause_done → IDLE con end_turn_o
    // ------------------------------------------------------------
    $display("\n--- Caso 3: Segunda carta manual SIN MATCH y pausa ---");
    // Primero volvemos a S_ONE seleccionando primera carta manual otra vez
    pulse_one_cycle(btn_sel_i);      // IDLE -> ONE
    @(posedge clk);
    expect_state(S_ONE, "Despues de seleccionar primera carta (manual, caso sin match)");

    // Ahora segunda selección manual SIN match
    cards_match_i = 1'b0;
    btn_sel_i     = 1'b1;
    @(posedge clk);
    assert(select_second_card_o==1) else $error("Esperaba select_second_card_o=1 en segunda selección manual");
    assert(start_pause_o==1)        else $error("Esperaba start_pause_o=1 cuando NO hay match");
    btn_sel_i = 1'b0;

    // Siguiente ciclo: debe ir a S_PAUSE
    @(posedge clk);
    expect_state(S_PAUSE, "Entro a PAUSE tras fallo");

    // Señalizar que terminó la pausa
    pause_done_i = 1'b1;
    @(posedge clk);
    // En este ciclo debe activar end_turn_o
    assert(end_turn_o==1) else $error("Esperaba end_turn_o=1 al terminar pausa");
    pause_done_i = 1'b0;

    // Próximo ciclo: regresar a IDLE
    @(posedge clk);
    expect_state(S_IDLE, "Regreso a IDLE tras PAUSE");

    // ------------------------------------------------------------
    // 4) Selección AUTOMÁTICA por timeout: 1.ª carta
    // IDLE --(time_up & auto_pick1_valid)--> ONE
    // ------------------------------------------------------------
    $display("\n--- Caso 4: Seleccion automatica de primera carta por timeout ---");
    time_up_i          = 1'b1;
    auto_pick1_valid_i = 1'b1;
    @(posedge clk);
    assert(auto_select_first_o==1) else $error("Esperaba auto_select_first_o=1 con time_up_i y auto_pick1_valid_i en IDLE");
    assert(restart_timer_o==1)     else $error("Esperaba restart_timer_o=1 al auto-seleccionar primera carta");
    // limpiar
    time_up_i          = 1'b0;
    auto_pick1_valid_i = 1'b0;
    @(posedge clk);
    expect_state(S_ONE, "Despues de auto-seleccion de primera carta");

    // ------------------------------------------------------------
    // 5) Segunda AUTOMÁTICA con MATCH: ONE --(time_up & auto_pick2_valid & cards_match)--> IDLE
    // ------------------------------------------------------------
    $display("\n--- Caso 5: Segunda automatica con MATCH ---");
    time_up_i          = 1'b1;
    auto_pick2_valid_i = 1'b1;
    cards_match_i      = 1'b1;
    @(posedge clk);
    assert(auto_select_second_o==1) else $error("Esperaba auto_select_second_o=1 con time_up_i y auto_pick2_valid_i");
    assert(match_found_o==1)        else $error("Esperaba match_found_o=1 en match automático");
    assert(extra_turn_o==1)         else $error("Esperaba extra_turn_o=1 en match automático");
    assert(restart_timer_o==1)      else $error("Esperaba restart_timer_o=1 en match automático");
    // limpiar
    time_up_i          = 1'b0;
    auto_pick2_valid_i = 1'b0;
    cards_match_i      = 1'b0;

    @(posedge clk);
    expect_state(S_IDLE, "Regreso a IDLE tras match automatico");

    // ------------------------------------------------------------
    // 6) Atajo match_happened_i desde S_ONE: debe volver a IDLE y reiniciar timer
    // ------------------------------------------------------------
    $display("\n--- Caso 6: Atajo match_happened_i ---");
    // Ir a S_ONE (primera carta manual)
    pulse_one_cycle(btn_sel_i);
    @(posedge clk);
    expect_state(S_ONE, "Antes de forzar match_happened_i");

    // Forzar atajo
    match_happened_i = 1'b1;
    @(posedge clk);
    // En este ciclo, el TB espera que restart_timer_o esté alto por la lógica del DUT
    assert(restart_timer_o==1) else $error("Esperaba restart_timer_o=1 cuando match_happened_i=1");
    match_happened_i = 1'b0;

    @(posedge clk);
    expect_state(S_IDLE, "Regreso a IDLE por match_happened_i");

    $display("\n*** Todas las pruebas finalizaron ***");
    # (5*CLK_PERIOD_NS);
    $finish;
  end

endmodule

Laboratorio3/simulation/modelsim/tb_fsm_control.vcd
$date
	Mon Sep 29 13:58:02 2025
$end
$version
	ModelSim Version 2020.1
$end
$timescale
	1ps
$end

$scope module tb_fsm_control $end
$var parameter 0 ! CLK_PERIOD_NS $end
$var parameter 2 " S_IDLE $end
$var parameter 2 # S_ONE $end
$var parameter 2 $ S_PAUSE $end
$var reg 1 % clk $end
$var reg 1 & rst_n $end
$var reg 1 ' btn_sel_i $end
$var reg 1 ( time_up_i $end
$var reg 1 ) cards_match_i $end
$var reg 1 * pause_done_i $end
$var reg 1 + auto_pick1_valid_i $end
$var reg 1 , auto_pick2_valid_i $end
$var reg 1 - match_happened_i $end
$var reg 1 . select_first_card_o $end
$var reg 1 / select_second_card_o $end
$var reg 1 0 auto_select_first_o $end
$var reg 1 1 auto_select_second_o $end
$var reg 1 2 match_found_o $end
$var reg 1 3 start_pause_o $end
$var reg 1 4 end_turn_o $end
$var reg 1 5 extra_turn_o $end
$var reg 1 6 restart_timer_o $end
$var reg 2 7 current_state_o [1:0] $end

$scope task apply_reset $end
$upscope $end

$scope function state_to_str $end
$upscope $end

$scope task expect_state $end
$upscope $end

$scope task pulse_one_cycle $end
$upscope $end

$scope task clear_inputs $end
$upscope $end

$scope module dut $end
$var parameter 2 8 S_IDLE $end
$var parameter 2 9 S_ONE $end
$var parameter 2 : S_PAUSE $end
$var wire 1 ; clk $end
$var wire 1 < rst_n $end
$var wire 1 = btn_sel_i $end
$var wire 1 > time_up_i $end
$var wire 1 ? cards_match_i $end
$var wire 1 @ pause_done_i $end
$var wire 1 A auto_pick1_valid_i $end
$var wire 1 B auto_pick2_valid_i $end
$var wire 1 C match_happened_i $end
$var reg 1 D select_first_card_o $end
$var reg 1 E select_second_card_o $end
$var reg 1 F auto_select_first_o $end
$var reg 1 G auto_select_second_o $end
$var reg 1 H match_found_o $end
$var reg 1 I start_pause_o $end
$var reg 1 J end_turn_o $end
$var reg 1 K extra_turn_o $end
$var reg 1 L restart_timer_o $end
$var reg 2 M current_state_o [1:0] $end
$var reg 2 N state [1:0] $end
$var reg 2 O next_state [1:0] $end
$upscope $end
$upscope $end
$enddefinitions $end
#0
$dumpvars
0%
x&
0'
0(
0)
0*
0+
0,
0-
0.
0/
00
01
02
03
04
05
06
bx 7
0D
0E
0F
0G
0H
0I
0J
0K
0L
bx M
bx N
b0 O
b0 "
b1 #
b10 $
b0 8
b1 9
b10 :
r10 !
0;
x<
0=
0>
0?
0@
0A
0B
0C
$end
#5000
1%
1;
0&
0<
b0 N
b0 M
b0 7
#10000
0%
0;
#15000
1%
1;
#20000
0%
0;
#25000
1%
1;
#30000
0%
0;
#35000
1%
1;
1&
1<
#40000
0%
0;
#45000
1%
1;
1'
1=
b1 O
1D
1.
#50000
0%
0;
#55000
1%
1;
0'
0=
b0 O
0D
0.
b1 N
b1 M
b1 7
b1 O
#60000
0%
0;
#65000
1%
1;
1)
1'
1?
1=
b0 O
1E
1H
1K
1L
16
15
12
1/
#70000
0%
0;
#75000
1%
1;
0'
0)
0=
0?
b1 O
0E
0H
0K
0L
06
05
02
0/
b0 N
b0 M
b0 7
b0 O
#80000
0%
0;
#85000
1%
1;
1'
1=
b1 O
1D
1.
#90000
0%
0;
#95000
1%
1;
0'
0=
b0 O
0D
0.
b1 N
b1 M
b1 7
b1 O
#100000
0%
0;
#105000
1%
1;
1'
1=
b10 O
1E
1I
13
1/
#110000
0%
0;
#115000
1%
1;
0'
0=
b1 O
0E
0I
03
0/
b10 N
b10 M
b10 7
b10 O
#120000
0%
0;
#125000
1%
1;
1*
1@
b0 O
1J
14
#130000
0%
0;
#135000
1%
1;
0*
0@
b10 O
0J
04
b0 N
b0 M
b0 7
b0 O
#140000
0%
0;
#145000
1%
1;
1(
1+
1>
1A
b1 O
1F
1L
16
10
#150000
0%
0;
#155000
1%
1;
0(
0+
0>
0A
b0 O
0F
0L
06
00
b1 N
b1 M
b1 7
b1 O
#160000
0%
0;
#165000
1%
1;
1(
1,
1)
1>
1B
1?
b0 O
1G
1H
1K
1L
16
15
12
11
#170000
0%
0;
#175000
1%
1;
0(
0,
0)
0>
0B
0?
b1 O
0G
0H
0K
0L
06
05
02
01
b0 N
b0 M
b0 7
b0 O
#180000
0%
0;
#185000
1%
1;
1'
1=
b1 O
1D
1.
#190000
0%
0;
#195000
1%
1;
0'
0=
b0 O
0D
0.
b1 N
b1 M
b1 7
b1 O
#200000
0%
0;
#205000
1%
1;
1-
1C
b0 O
1L
16
#210000
0%
0;
#215000
1%
1;
0-
0C
b1 O
0L
06
b0 N
b0 M
b0 7
b0 O
#220000
0%
0;
#225000
1%
1;
#230000
0%
0;
#235000
1%
1;
#240000
0%
0;
#245000
1%
1;
#250000
0%
0;
#255000
1%
1;
#260000
0%
0;
#265000
1%
1;
#270000
0%
0;
#275000
1%
1;
#280000
0%
0;
#285000
1%
1;
#290000
0%
0;
#295000
1%
1;
12
#300000
0%
0;
#305000
1%
1;
#310000
0%
0;
#315000
1%
1;
#320000
0%
0;
#325000
1%
1;
1(
1>
#330000
0%
0;
#335000
1%
1;
#340000
0%
0;
#345000
1%
1;
1'
1=
b1 O
1D
1.
#350000
0%
0;
#355000
1%
1;
b1 N
b1 M
b1 7
b10 O
0D
1E
1I
13
1/
0.
#360000
0%
0;
#365000
1%
1;
b10 N
b10 M
b10 7
0E
0I
03
0/
0'
0=
